BASEoriginaldata/__init__.py
BASEoriginaldata/data/LICENSE
BASEoriginaldata/data/__init__.py
BASEoriginaldata/data/aBASE-113-input.xlsx
BASEoriginaldata/data/cBASE-113-input.xlsx
BASEoriginaldata/data/SeqData/28GH81_A01.ab1
BASEoriginaldata/data/SeqData/28GH82_D03.ab1
BASEoriginaldata/data/SeqData/28GH82_D04.ab1
BASEoriginaldata/data/SeqData/28GH82_D05.ab1
BASEoriginaldata/data/SeqData/28GH82_D06.ab1
BASEoriginaldata/data/SeqData/28GH82_D07.ab1
BASEoriginaldata/data/SeqData/28GH82_D08.ab1
BASEoriginaldata/data/SeqData/28GH82_D09.ab1
BASEoriginaldata/data/SeqData/28GH82_D10.ab1
BASEoriginaldata/data/SeqData/28GH82_D12.ab1
BASEoriginaldata/data/SeqData/28GH82_E01.ab1
BASEoriginaldata/data/SeqData/28GH82_E02.ab1
BASEoriginaldata/data/SeqData/28GH82_E03.ab1
BASEoriginaldata/data/SeqData/28GH82_E04.ab1
BASEoriginaldata/data/SeqData/28GH82_E05.ab1
BASEoriginaldata/data/SeqData/28GH82_E06.ab1
BASEoriginaldata/data/SeqData/28GH82_E07.ab1
BASEoriginaldata/data/SeqData/28GH82_E08.ab1
BASEoriginaldata/data/SeqData/28GH82_E09.ab1
BASEoriginaldata/data/SeqData/28GH84_D12.ab1
BASEoriginaldata/data/SeqData/28GH84_E04.ab1
BASEoriginaldata/data/SeqData/34GC12.ab1
BASEoriginaldata/data/SeqData/34GC13.ab1
BASEoriginaldata/data/SeqData/34GC15.ab1
BASEoriginaldata/data/SeqData/34GC36.ab1
BASEoriginaldata/data/SeqData/34GC37.ab1
BASEoriginaldata/data/SeqData/34GC38.ab1
BASEoriginaldata/data/SeqData/47JB64.ab1
BASEoriginaldata/data/SeqData/47JB81.ab1
BASEoriginaldata/data/SeqData/47JB82.ab1
BASEoriginaldata/data/SeqData/47JB83.ab1
BASEoriginaldata/data/SeqData/47JB84.ab1
BASEoriginaldata/data/SeqData/47JB91.ab1
BASEoriginaldata/data/SeqData/47JB92.ab1
BASEoriginaldata/data/SeqData/47JB93.ab1
BASEoriginaldata/data/SeqData/47JB94.ab1
BASEoriginaldata/data/SeqData/47JB95.ab1
BASEoriginaldata/data/SeqData/47JB96.ab1
BASEoriginaldata/data/SeqData/47JB97.ab1
BASEoriginaldata/data/SeqData/47JB98.ab1
BASEoriginaldata/data/SeqData/47JB99.ab1
BASEoriginaldata/data/SeqData/47JC00.ab1
BASEoriginaldata-2.0.0.dev3.dist-info/LICENSE.txt
BASEoriginaldata-2.0.0.dev3.dist-info/METADATA
BASEoriginaldata-2.0.0.dev3.dist-info/WHEEL
BASEoriginaldata-2.0.0.dev3.dist-info/top_level.txt
BASEoriginaldata-2.0.0.dev3.dist-info/RECORD
