Metadata-Version: 2.1
Name: BASEoriginaldata
Version: 2.0.0.dev3
Summary: BASEoriginaldata
Author-email: Johannes <johannes-programming@mailfence.com>
License:                     GNU GENERAL PUBLIC LICENSE
Project-URL: Documentation, https://pypi.org/project/BASEoriginaldata
Project-URL: Download, https://pypi.org/project/BASEoriginaldata/#files
Project-URL: Source, https://github.com/johannes-programming/BASEoriginaldata
Classifier: Development Status :: 3 - Alpha
Classifier: License :: OSI Approved :: MIT License
Classifier: Programming Language :: Python
Classifier: Programming Language :: Python :: 3
Classifier: Programming Language :: Python :: 3 :: Only
Requires-Python: >=3.7
License-File: LICENSE.txt
